cc_server/__init__.py
cc_server/__main__.py
cc_server/main.py
cookiecutter_server-1.2.2.dist-info/LICENSE
cookiecutter_server-1.2.2.dist-info/METADATA
cookiecutter_server-1.2.2.dist-info/WHEEL
cookiecutter_server-1.2.2.dist-info/entry_points.txt
cookiecutter_server-1.2.2.dist-info/RECORD
