Metadata-Version: 2.3
Name: cookiecutter-server
Version: 1.2.2
Summary: A local development server to get live previews of [cookiecutter templates](https://github.com/cookiecutter/cookiecutter).
License: Apache-2.0
Author: Sebastian Straub
Author-email: sebastian.straub@alexanderthamm.com
Requires-Python: >=3.9,<3.14
Classifier: Development Status :: 4 - Beta
Classifier: Environment :: Console
Classifier: Intended Audience :: Developers
Classifier: License :: OSI Approved :: Apache Software License
Classifier: Programming Language :: Python
Classifier: Programming Language :: Python :: 3
Classifier: Programming Language :: Python :: 3.9
Classifier: Programming Language :: Python :: 3.10
Classifier: Programming Language :: Python :: 3.11
Classifier: Programming Language :: Python :: 3.12
Classifier: Programming Language :: Python :: 3.13
Classifier: Programming Language :: Python :: 3 :: Only
Classifier: Topic :: Software Development
Classifier: Topic :: Software Development :: Libraries :: Python Modules
Requires-Dist: cookiecutter (>=2.6.0,<3.0.0)
Requires-Dist: dirsync (>=2.2.5,<3.0.0)
Requires-Dist: pyyaml (>=6.0.2,<7.0.0)
Requires-Dist: typer[all] (>=0.15.1,<0.16.0)
Requires-Dist: watchdog (>=6.0.0,<7.0.0)
